whispa_app/__init__.py
whispa_app/batch.py
whispa_app/config.py
whispa_app/device.py
whispa_app/export.py
whispa_app/exporters.py
whispa_app/main.py
whispa_app/prefetch.py
whispa_app/realtime.py
whispa_app/run.py
whispa_app/telemetry.py
whispa_app/transcription.py
whispa_app/translation.py
whispa_app/utils.py
whispa_app/assets/icon.bmp
whispa_app/assets/icon.ico
whispa_app/assets/icon.png
whispa_app/assets/wizard_image.bmp
whispa_app/assets/wizard_small.bmp
whispa_app/assets/installer/icon.bmp
whispa_app/assets/installer/icon.ico
whispa_app/assets/installer/icon.png
whispa_app/assets/installer/wizard_image.bmp
whispa_app/assets/installer/wizard_small.bmp
whispa_app/ui/__init__.py
whispa_app/ui/file_input.py
whispa_app/ui/header.py
whispa_app/ui/panels.py
whispa_app/ui/shortcuts.py
whispa_app/ui/theme.py
whispa_app-2.2.0.dist-info/licenses/LICENSE
whispa_app-2.2.0.dist-info/licenses/License.txt
whispa_app-2.2.0.dist-info/METADATA
whispa_app-2.2.0.dist-info/WHEEL
whispa_app-2.2.0.dist-info/entry_points.txt
whispa_app-2.2.0.dist-info/top_level.txt
whispa_app-2.2.0.dist-info/RECORD
