Metadata-Version: 2.4
Name: whispa_app
Version: 2.2.0
Summary: GUI for Whisper transcription & MarianMT translation
Home-page: https://github.com/damoojeje/whispa_app
Author: Damilare Eniolabi
Author-email: Damilare Eniolabi <damilareeniolabi@gmail.com>
License-Expression: MIT
Project-URL: Homepage, https://github.com/damoojeje/whispa_app
Project-URL: Bug Tracker, https://github.com/damoojeje/whispa_app/issues
Keywords: whisper,transcription,translation,GUI,speech-to-text
Classifier: Programming Language :: Python :: 3
Classifier: Programming Language :: Python :: 3.10
Classifier: Operating System :: Microsoft :: Windows
Classifier: Topic :: Multimedia :: Sound/Audio
Classifier: Topic :: Scientific/Engineering :: Artificial Intelligence
Classifier: Intended Audience :: End Users/Desktop
Requires-Python: >=3.10
License-File: LICENSE
License-File: License.txt
Requires-Dist: customtkinter>=5.1.1
Requires-Dist: psutil>=5.9.0
Requires-Dist: faster-whisper>=0.7.0
Requires-Dist: transformers>=4.31.0
Requires-Dist: huggingface-hub>=0.14.1
Requires-Dist: sentencepiece>=0.1.97
Requires-Dist: requests>=2.28.0
Requires-Dist: sacremoses>=0.0.53
Requires-Dist: torch>=2.0.1; sys_platform != "win32"
Requires-Dist: torch==2.0.1+cpu; sys_platform == "win32"
Provides-Extra: gpu
Requires-Dist: torch>=2.0.1; extra == "gpu"
Dynamic: author
Dynamic: home-page
Dynamic: license-file
Dynamic: requires-python
